smartcalc/__init__.py
smartcalc/core.py
smartcalc-0.1.2.dist-info/licenses/LICENSE
smartcalc-0.1.2.dist-info/METADATA
smartcalc-0.1.2.dist-info/WHEEL
smartcalc-0.1.2.dist-info/entry_points.txt
smartcalc-0.1.2.dist-info/top_level.txt
smartcalc-0.1.2.dist-info/RECORD
