Metadata-Version: 2.4
Name: smartcalc
Version: 0.1.2
Summary: A minimal calculator with keyboard control dark & lite themes.
Author-email: Sergey Samoylov <linews@yandex.ru>
License: GPL-3.0-or-later
Requires-Python: >=3.10
License-File: LICENSE
Requires-Dist: build>=1.2.2.post1
Requires-Dist: pygame>=2.5
Requires-Dist: twine>=6.1.0
Dynamic: license-file
